LICENSE
README.md
setup.py
yasiu/__init__.py
yasiu/time.py
yasiu_time.egg-info/PKG-INFO
yasiu_time.egg-info/SOURCES.txt
yasiu_time.egg-info/dependency_links.txt
yasiu_time.egg-info/top_level.txt